{
  "project_info": {
    "project_number": "662648386054",
    "project_id": "iot-63-8a438",
    "storage_bucket": "iot-63-8a438.firebasestorage.app"
  },
  "client": [
    {
      "client_info": {
        "mobilesdk_app_id": "1:662648386054:android:0409ba8fe14f12800fc987",
        "android_client_info": {
          "package_name": "com.example.myapp"
        }
      },
      "oauth_client": [],
      "api_key": [
        {
          "current_key": "AIzaSyCLq-Iu2vH_H6l1BSYLnGZR0glPhXcYCpI"
        }
      ],
      "services": {
        "appinvite_service": {
          "other_platform_oauth_client": []
        }
      }
    },
    {
      "client_info": {
        "mobilesdk_app_id": "1:662648386054:android:60c837571cc74e740fc987",
        "android_client_info": {
          "package_name": "com.example.petrol_customer_app"
        }
      },
      "oauth_client": [],
      "api_key": [
        {
          "current_key": "AIzaSyCLq-Iu2vH_H6l1BSYLnGZR0glPhXcYCpI"
        }
      ],
      "services": {
        "appinvite_service": {
          "other_platform_oauth_client": []
        }
      }
    }
  ],
  "configuration_version": "1"
}